[
  {
    "id": "6fd1f10b-ca0f-4f6a-a274-263dc46a4eaa",
    "name": "Arroz Branco Tipo 1",
    "category": "Alimentos",
    "brand": "Tio João",
    "unit": "kg",
    "averagePrice": 6.99,
    "barcode": "7891234567890",
    "description": "Arroz branco tipo 1, pacote 5kg",
    "active": true,
    "createdAt": "2025-09-21T23:10:58.702Z",
    "updatedAt": "2025-09-21T23:10:58.705Z"
  },
  {
    "id": "bee900c5-6034-4db0-9935-843620734b03",
    "name": "Feijão Carioca",
    "category": "Alimentos",
    "brand": "Camil",
    "unit": "kg",
    "averagePrice": 8.5,
    "barcode": "7891234567891",
    "description": "Feijão carioca tipo 1, pacote 1kg",
    "active": true,
    "createdAt": "2025-09-21T23:10:58.704Z",
    "updatedAt": "2025-09-21T23:10:58.721Z"
  },
  {
    "id": "b2349a06-822b-43a4-8dab-70b9ac53280c",
    "name": "Açúcar Cristal",
    "category": "Alimentos",
    "brand": "União",
    "unit": "kg",
    "averagePrice": 4.99,
    "barcode": "7891234567892",
    "description": "Açúcar cristal refinado, pacote 1kg",
    "active": true,
    "createdAt": "2025-09-21T23:10:58.704Z",
    "updatedAt": "2025-09-21T23:10:58.734Z"
  },
  {
    "id": "1161b48a-951a-4de8-ae9a-7d21d561e963",
    "name": "Leite Integral UHT",
    "category": "Alimentos",
    "brand": "Nestle",
    "unit": "litro",
    "averagePrice": 4.5,
    "barcode": "7891234567893",
    "description": "Leite integral UHT, caixa 1L",
    "active": true,
    "createdAt": "2025-09-21T23:10:58.704Z",
    "updatedAt": "2025-09-21T23:10:58.748Z"
  },
  {
    "id": "5c66e92b-f391-4378-80e5-d29661635b96",
    "name": "Óleo de Soja",
    "category": "Alimentos",
    "brand": "Soya",
    "unit": "litro",
    "averagePrice": 5.99,
    "barcode": "7891234567894",
    "description": "Óleo de soja refinado, garrafa 900ml",
    "active": true,
    "createdAt": "2025-09-21T23:10:58.704Z",
    "updatedAt": "2025-09-21T23:10:58.762Z"
  },
  {
    "id": "28f8d4f0-b993-49c0-a59e-ebf7ed8481b5",
    "name": "Detergente Líquido",
    "category": "Limpeza",
    "brand": "Ypê",
    "unit": "un",
    "averagePrice": 2.99,
    "barcode": "7891234567895",
    "description": "Detergente líquido neutro, frasco 500ml",
    "active": true,
    "createdAt": "2025-09-21T23:10:58.704Z",
    "updatedAt": "2025-09-21T23:10:58.825Z"
  },
  {
    "id": "532bf3e2-442c-4f88-a474-66126e674fea",
    "name": "Sabão em Pó",
    "category": "Limpeza",
    "brand": "OMO",
    "unit": "kg",
    "averagePrice": 12.99,
    "barcode": "7891234567896",
    "description": "Sabão em pó concentrado, caixa 1kg",
    "active": true,
    "createdAt": "2025-09-21T23:10:58.704Z",
    "updatedAt": "2025-09-21T23:10:58.838Z"
  },
  {
    "id": "6e584107-80f9-41d6-b346-0e249be42aaa",
    "name": "Amaciante de Roupa",
    "category": "Limpeza",
    "brand": "Comfort",
    "unit": "litro",
    "averagePrice": 8.99,
    "barcode": "7891234567897",
    "description": "Amaciante concentrado, frasco 2L",
    "active": true,
    "createdAt": "2025-09-21T23:10:58.704Z",
    "updatedAt": "2025-09-21T23:10:58.851Z"
  },
  {
    "id": "a95274f2-1d7a-48fa-a599-fa7d8d80caa7",
    "name": "Desinfetante",
    "category": "Limpeza",
    "brand": "Pinho Sol",
    "unit": "litro",
    "averagePrice": 6.99,
    "barcode": "7891234567898",
    "description": "Desinfetante pinho, frasco 1L",
    "active": true,
    "createdAt": "2025-09-21T23:10:58.704Z",
    "updatedAt": "2025-09-21T23:10:58.864Z"
  },
  {
    "id": "6d33c54c-8bcf-4f4b-84cc-f60f5bd35d23",
    "name": "Esponja de Aço",
    "category": "Limpeza",
    "brand": "Bombril",
    "unit": "un",
    "averagePrice": 3.5,
    "barcode": "7891234567899",
    "description": "Esponja de aço, pacote com 8 unidades",
    "active": true,
    "createdAt": "2025-09-21T23:10:58.704Z",
    "updatedAt": "2025-09-21T23:10:58.877Z"
  },
  {
    "id": "aeca3c35-81d4-49df-ad12-885eeb0c3313",
    "name": "Pasta de Dente",
    "category": "Higiene",
    "brand": "Colgate",
    "unit": "un",
    "averagePrice": 4.99,
    "barcode": "7891234567800",
    "description": "Pasta de dente total 12, tubo 90g",
    "active": true,
    "createdAt": "2025-09-21T23:10:58.704Z",
    "updatedAt": "2025-09-21T23:10:58.890Z"
  },
  {
    "id": "47e1e364-7332-48e1-b159-0be613f5c3aa",
    "name": "Shampoo",
    "category": "Higiene",
    "brand": "Seda",
    "unit": "un",
    "averagePrice": 12.99,
    "barcode": "7891234567801",
    "description": "Shampoo hidratação, frasco 325ml",
    "active": true,
    "createdAt": "2025-09-21T23:10:58.704Z",
    "updatedAt": "2025-09-21T23:10:58.903Z"
  },
  {
    "id": "c4674f5b-a6b3-474b-b3c4-d0b29479cec1",
    "name": "Sabonete",
    "category": "Higiene",
    "brand": "Dove",
    "unit": "un",
    "averagePrice": 2.5,
    "barcode": "7891234567802",
    "description": "Sabonete hidratante, barra 90g",
    "active": true,
    "createdAt": "2025-09-21T23:10:58.704Z",
    "updatedAt": "2025-09-21T23:10:58.918Z"
  },
  {
    "id": "1b1f4752-6d0d-4cd5-a640-aaff15e22fb1",
    "name": "Papel Higiênico",
    "category": "Higiene",
    "brand": "Neve",
    "unit": "un",
    "averagePrice": 18.99,
    "barcode": "7891234567803",
    "description": "Papel higiênico folha dupla, pacote 12 rolos",
    "active": true,
    "createdAt": "2025-09-21T23:10:58.704Z",
    "updatedAt": "2025-09-21T23:10:58.932Z"
  },
  {
    "id": "ba7acf8b-b727-4b2e-bdf8-3aa4d7b8619e",
    "name": "Refrigerante Cola",
    "category": "Bebidas",
    "brand": "Coca-Cola",
    "unit": "litro",
    "averagePrice": 6.99,
    "barcode": "7891234567804",
    "description": "Refrigerante cola, garrafa 2L",
    "active": true,
    "createdAt": "2025-09-21T23:10:58.704Z",
    "updatedAt": "2025-09-21T23:10:58.946Z"
  },
  {
    "id": "1bb24679-98b5-4837-8ed7-8c82d6662262",
    "name": "Suco de Laranja",
    "category": "Bebidas",
    "brand": "Tang",
    "unit": "un",
    "averagePrice": 3.99,
    "barcode": "7891234567805",
    "description": "Suco em pó sabor laranja, envelope 25g",
    "active": true,
    "createdAt": "2025-09-21T23:10:58.704Z",
    "updatedAt": "2025-09-21T23:10:58.959Z"
  },
  {
    "id": "05db433f-735f-4a29-82ef-c34b23cd8c9f",
    "name": "Água Mineral",
    "category": "Bebidas",
    "brand": "Crystal",
    "unit": "litro",
    "averagePrice": 2.5,
    "barcode": "7891234567806",
    "description": "Água mineral natural, garrafa 1,5L",
    "active": true,
    "createdAt": "2025-09-21T23:10:58.704Z",
    "updatedAt": "2025-09-21T23:10:58.972Z"
  },
  {
    "id": "611880f6-b0da-45a9-8268-a2254d5b63e3",
    "name": "Pão de Forma",
    "category": "Padaria",
    "brand": "Pullman",
    "unit": "un",
    "averagePrice": 5.99,
    "barcode": "7891234567807",
    "description": "Pão de forma integral, pacote 500g",
    "active": true,
    "createdAt": "2025-09-21T23:10:58.704Z",
    "updatedAt": "2025-09-21T23:10:58.986Z"
  },
  {
    "id": "d27ebe68-9ac1-4c83-bf25-a0314b9f687c",
    "name": "Biscoito Recheado",
    "category": "Padaria",
    "brand": "Oreo",
    "unit": "un",
    "averagePrice": 4.5,
    "barcode": "7891234567808",
    "description": "Biscoito recheado chocolate, pacote 144g",
    "active": true,
    "createdAt": "2025-09-21T23:10:58.704Z",
    "updatedAt": "2025-09-21T23:10:59.000Z"
  },
  {
    "id": "0f55b9e3-ae75-418c-9515-43d50795c777",
    "name": "Bolacha Cream Cracker",
    "category": "Padaria",
    "brand": "Adria",
    "unit": "un",
    "averagePrice": 3.99,
    "barcode": "7891234567809",
    "description": "Bolacha cream cracker, pacote 200g",
    "active": true,
    "createdAt": "2025-09-21T23:10:58.704Z",
    "updatedAt": "2025-09-21T23:10:59.013Z"
  }
]
